__init__.py
ztffp.py
ztffp-2.0.2.dist-info/LICENSE.txt
ztffp-2.0.2.dist-info/METADATA
ztffp-2.0.2.dist-info/WHEEL
ztffp-2.0.2.dist-info/top_level.txt
ztffp-2.0.2.dist-info/RECORD
