Metadata-Version: 2.1
Name: ztffp
Version: 2.0.2
Summary: ZTF Forced-Photometry library (Unaffiliated)
Author-email: "Michael C. Stroh" <ztffp@michaelcstroh.com>
License: GNU GENERAL PUBLIC LICENSE
Project-URL: Homepage, https://github.com/mcstroh/ztffp
Project-URL: Bug Reports, https://github.com/mcstroh/ztffp/issues
Project-URL: Source, https://github.com/mcstroh/ztffp/
Keywords: astronomy
Classifier: Development Status :: 5 - Production/Stable
Classifier: License :: OSI Approved :: GNU General Public License v3 (GPLv3)
Classifier: Programming Language :: Python :: 3.10
Classifier: Programming Language :: Python :: 3.11
Classifier: Programming Language :: Python :: 3.12
Requires-Python: >=3.10
License-File: LICENSE.txt
Requires-Dist: astropy >=4.3.0
Requires-Dist: lxml >=4.9.0
Requires-Dist: matplotlib >=3.5.3
Requires-Dist: numpy >=1.21.0
Requires-Dist: pandas >=1.3.5
